kogi-canvas/__init__.py
kogi-canvas/google_check.py
kogi-canvas/pycanvas.py
kogi_canvas/__init__.py
kogi_canvas/canvas.py
kogi_canvas/google_check.py
kogi_canvas/images.py
kogi_canvas/jsmath.py
kogi_canvas/movies.py
kogi_canvas/othello.py
kogi_canvas/pycanvas.py
kogi_canvas-0.2.2.dist-info/LICENSE
kogi_canvas-0.2.2.dist-info/METADATA
kogi_canvas-0.2.2.dist-info/WHEEL
kogi_canvas-0.2.2.dist-info/top_level.txt
kogi_canvas-0.2.2.dist-info/RECORD
