Metadata-Version: 2.1
Name: kogi-canvas
Version: 0.2.2
Summary: Canvas from KOGI
Home-page: https://github.com/kuramitsulab/kogi-canvas
Author: Kimio Kuramitsu
License: Apache
Classifier: Development Status :: 4 - Beta
Classifier: License :: OSI Approved :: Apache Software License
Classifier: Framework :: IPython
Classifier: Programming Language :: Python :: 3.7
Classifier: Programming Language :: Python :: 3.8
Classifier: Programming Language :: Python :: 3.9
Classifier: Programming Language :: Python :: 3.10
Classifier: Programming Language :: Python :: 3.11
Classifier: Intended Audience :: Education
License-File: LICENSE
Requires-Dist: requests
Requires-Dist: Pillow
Requires-Dist: ffmpeg-python
